blobclass/__init__.py
blobclass/blob_class.py
blobwork/__init__.py
blobwork/blob_work.py
blobworld/__init__.py
blobworld/blob_world.py
blobworld/blobicon.png
blobworld/end.wav
blobworld/kill.wav
blobworld/pause.wav
blobworld/start.wav
blobworld-1.2.3.data/scripts/blob_world.py
blobworld-1.2.3.dist-info/LICENSE.md
blobworld-1.2.3.dist-info/METADATA
blobworld-1.2.3.dist-info/WHEEL
blobworld-1.2.3.dist-info/top_level.txt
blobworld-1.2.3.dist-info/RECORD
